jsonpath_nz/__init__.py
jsonpath_nz/flatten_dict.py
jsonpath_nz/jprint.py
jsonpath_nz/log.py
jsonpath_nz/merge_json.py
jsonpath_nz/parse_dict.py
jsonpath_nz/parse_jsonpath.py
jsonpath_nz/xml_to_json.py
jsonpath_nz-1.0.6.dist-info/LICENSE
jsonpath_nz-1.0.6.dist-info/METADATA
jsonpath_nz-1.0.6.dist-info/WHEEL
jsonpath_nz-1.0.6.dist-info/RECORD
