Metadata-Version: 2.1
Name: jsonpath-nz
Version: 1.0.6
Summary: A comprehensive Python library for bidirectional conversion between JSON objects and JSONPath expressions, with advanced features for complex data manipulation, XML processing, JSON merging, and enhanced logging capabilities
Home-page: https://github.com/arusatech/jsonpath-nz
License: MIT
Keywords: json,jsonpath,converter,dict,xml,merge,logging,xml2json,xml_to_json,parse_jsonpath,parse_dict,merge_json,flatten_dict
Author: Yakub Mohammad
Author-email: yakub@arusatech.com> <arusatechnology@gmail.com
Requires-Python: >=3.7
Classifier: Development Status :: 5 - Production/Stable
Classifier: Intended Audience :: Developers
Classifier: License :: OSI Approved :: MIT License
Classifier: Programming Language :: Python :: 3
Classifier: Programming Language :: Python :: 3.7
Classifier: Programming Language :: Python :: 3.8
Classifier: Programming Language :: Python :: 3.9
Classifier: Programming Language :: Python :: 3.10
Classifier: Programming Language :: Python :: 3.11
Classifier: Programming Language :: Python :: 3.12
Classifier: Programming Language :: Python :: 3.13
Classifier: Programming Language :: Python :: 3.14
Classifier: Topic :: Software Development :: Libraries :: Python Modules
Project-URL: Documentation, https://github.com/arusatech/jsonpath-nz#readme
Project-URL: Repository, https://github.com/arusatech/jsonpath-nz
